---
title: "字节码是什么？从.java到.class的编译过程"
date: 2025-11-21T17:00:00+08:00
draft: false
tags: ["JVM", "字节码", "javac", "class文件格式"]
categories: ["技术"]
description: "深入理解字节码的本质：从javac编译过程到class文件格式，从常量池到字节码指令，掌握Java编译的核心机制"
series: ["JVM从入门到精通"]
weight: 4
stage: 1
stageTitle: "基础认知篇"
---

## 引言

### 为什么要学习这个主题？

在前面的文章中，我们多次提到"字节码"这个概念。但字节码到底是什么？

想象一下：
- 为什么`.class`文件比`.java`文件还大？
- `javac`编译器到底做了什么？
- 字节码长什么样子？能看懂吗？

理解字节码是理解JVM的关键。就像理解汇编语言能帮助理解CPU一样，理解字节码能帮助我们：
- 优化代码性能
- 理解JVM的执行机制
- 排查诡异的BUG
- 实现字节码增强（如AOP）

### 你将学到什么？

- ✅ 字节码的本质和作用
- ✅ javac编译器的工作流程
- ✅ class文件的格式结构
- ✅ 如何查看和理解字节码
- ✅ 常见的字节码指令

---

## 一、什么是字节码？

### 1.1 字节码的定义

**字节码（Bytecode）**：一种介于源代码和机器码之间的中间表示形式。

```
源代码（人类可读）
    ↓ javac编译
字节码（JVM可读）
    ↓ JVM解释/编译
机器码（CPU可读）
```

**特点**：
- 不是源代码，不是机器码
- 平台无关（跨平台的关键）
- 紧凑高效（比源代码小）
- 包含完整的类型信息

### 1.2 为什么需要字节码？

#### 方案1：直接编译成机器码（C/C++方式）

```
.java → [编译器] → .exe (Windows机器码)
                → .out (Linux机器码)
                → .app (macOS机器码)
```

**缺点**：
- 需要为每个平台单独编译
- 无法跨平台运行
- 无法在运行时优化

#### 方案2：直接解释执行源代码（Python方式）

```
.java → [解释器] → 逐行解释执行
```

**缺点**：
- 执行效率低
- 无法进行静态类型检查
- 无法提前优化

#### 方案3：字节码中间层（Java方式）✅

```
.java → [javac] → .class (字节码)
                   ↓
            [JVM解释/JIT] → 机器码
```

**优点**：
- 跨平台（一次编译，到处运行）
- 高效执行（JIT编译优化）
- 安全验证（字节码校验）
- 动态加载（运行时加载类）

---

## 二、javac编译过程

### 2.1 javac编译器的工作流程

```
.java文件
    ↓
1️⃣ 词法分析 (Lexical Analysis)
    ↓
Token流
    ↓
2️⃣ 语法分析 (Syntax Analysis)
    ↓
抽象语法树 (AST)
    ↓
3️⃣ 语义分析 (Semantic Analysis)
    ↓
注解抽象语法树
    ↓
4️⃣ 字节码生成 (Code Generation)
    ↓
.class文件（字节码）
```

### 2.2 详细步骤解析

#### 步骤1：词法分析

**作用**：将源代码分解成Token（词法单元）

**示例**：
```java
int count = 10;
```

**分解为Token**：
```
int     → 关键字
count   → 标识符
=       → 运算符
10      → 整数字面量
;       → 分隔符
```

#### 步骤2：语法分析

**作用**：根据Token构建抽象语法树（AST）

**示例AST**：
```
变量声明
├── 类型: int
├── 变量名: count
└── 初始值: 10
```

#### 步骤3：语义分析

**作用**：类型检查、变量赋值检查、常量折叠等

**检查内容**：
- 类型是否匹配
- 变量是否已声明
- 方法调用是否正确
- 泛型类型检查

**示例**：
```java
int count = "hello";  // ❌ 类型不匹配，编译报错
```

#### 步骤4：字节码生成

**作用**：将AST转换为字节码指令

**示例**：
```java
int count = 10;
```

**生成字节码**：
```
bipush 10      // 将常量10推入操作数栈
istore_1       // 将栈顶的值存储到局部变量表的1号位置
```

---

## 三、class文件格式

### 3.1 class文件结构

**class文件**：一个二进制文件，严格按照JVM规范定义的格式。

```
ClassFile {
    u4             magic;                    // 魔数：0xCAFEBABE
    u2             minor_version;            // 次版本号
    u2             major_version;            // 主版本号
    u2             constant_pool_count;      // 常量池计数
    cp_info        constant_pool[];          // 常量池
    u2             access_flags;             // 访问标志
    u2             this_class;               // 类索引
    u2             super_class;              // 父类索引
    u2             interfaces_count;         // 接口计数
    u2             interfaces[];             // 接口索引表
    u2             fields_count;             // 字段计数
    field_info     fields[];                 // 字段表
    u2             methods_count;            // 方法计数
    method_info    methods[];                // 方法表
    u2             attributes_count;         // 属性计数
    attribute_info attributes[];             // 属性表
}
```

**说明**：
- `u2`：2字节无符号整数
- `u4`：4字节无符号整数
- `[]`：数组

### 3.2 魔数（Magic Number）

**固定值**：`0xCAFEBABE`

**作用**：标识这是一个class文件

**为什么是CAFEBABE？**
- 传说是Java之父James Gosling在咖啡馆想出来的
- CAFE = 咖啡，BABE = 宝贝

**验证**：
```bash
# 查看class文件的前4个字节
xxd -l 4 HelloWorld.class
```

**输出**：
```
00000000: cafe babe
```

### 3.3 版本号

**格式**：主版本号.次版本号

**对应关系**：
```
Java 8  → 52.0
Java 11 → 55.0
Java 17 → 61.0
Java 21 → 65.0
```

**向后兼容**：高版本JVM可以运行低版本class文件，反之不行。

### 3.4 常量池（Constant Pool）

**作用**：存储字面量和符号引用

**包含内容**：
- 字符串常量
- 类和接口的全限定名
- 字段和方法的名称和描述符
- 数字常量

**示例**：
```java
public class Example {
    private String name = "Alice";
}
```

**常量池**：
```
#1 = Methodref          #4.#20         // java/lang/Object."<init>":()V
#2 = String             #21            // Alice
#3 = Fieldref           #22.#23        // Example.name:Ljava/lang/String;
#4 = Class              #24            // java/lang/Object
...
```

### 3.5 方法表（Methods）

**包含**：
- 方法名
- 方法描述符（参数类型、返回类型）
- 访问标志（public、private等）
- **Code属性**（字节码指令）

---

## 四、实战：查看和解读字节码

### 4.1 使用javap查看字节码

**示例代码**：
```java
public class BytecodeDemo {
    private int count = 0;

    public void increment() {
        count++;
    }

    public int getCount() {
        return count;
    }
}
```

**编译**：
```bash
javac BytecodeDemo.java
```

**查看字节码**：
```bash
javap -c -v BytecodeDemo.class
```

**输出（节选）**：
```
Classfile BytecodeDemo.class
  Last modified 2025-11-21; size 428 bytes
  MD5 checksum 1234567890abcdef
  Compiled from "BytecodeDemo.java"
public class BytecodeDemo
  minor version: 0
  major version: 61                   ← Java 17
  flags: (0x0021) ACC_PUBLIC, ACC_SUPER
  this_class: #2                       // BytecodeDemo
  super_class: #4                      // java/lang/Object
  ...

Constant pool:
   #1 = Methodref          #4.#20     // java/lang/Object."<init>":()V
   #2 = Class              #21        // BytecodeDemo
   #3 = Fieldref           #2.#22     // BytecodeDemo.count:I
   ...

{
  public void increment();
    descriptor: ()V
    flags: (0x0001) ACC_PUBLIC
    Code:
      stack=3, locals=1, args_size=1
         0: aload_0                   // 加载this
         1: dup                       // 复制this
         2: getfield      #3          // 获取字段count
         5: iconst_1                  // 常量1推入栈
         6: iadd                      // 执行加法
         7: putfield      #3          // 将结果存储到count
        10: return
      LineNumberTable:
        line 5: 0
        line 6: 10
      LocalVariableTable:
        Start  Length  Slot  Name   Signature
            0      11     0  this   LBytecodeDemo;

  public int getCount();
    descriptor: ()I
    flags: (0x0001) ACC_PUBLIC
    Code:
      stack=1, locals=1, args_size=1
         0: aload_0                   // 加载this
         1: getfield      #3          // 获取字段count
         4: ireturn                   // 返回int值
      LineNumberTable:
        line 9: 0
      LocalVariableTable:
        Start  Length  Slot  Name   Signature
            0       5     0  this   LBytecodeDemo;
}
```

### 4.2 解读字节码指令

#### increment()方法的字节码

```
0: aload_0        // 将局部变量表slot 0（this）加载到操作数栈
1: dup            // 复制栈顶元素（this）
2: getfield #3    // 获取this.count字段，压入栈
5: iconst_1       // 将常量1压入栈
6: iadd           // 弹出两个int，相加，结果压入栈
7: putfield #3    // 弹出栈顶的值，赋值给this.count
10: return        // 方法返回
```

**操作数栈变化**：
```
初始：[]
aload_0:  [this]
dup:      [this, this]
getfield: [this, count值]
iconst_1: [this, count值, 1]
iadd:     [this, count值+1]
putfield: []
return:   []
```

### 4.3 常见字节码指令

#### 加载和存储指令

| 指令 | 作用 | 示例 |
|-----|------|------|
| `aload_n` | 加载引用类型到栈 | `aload_0`（this） |
| `iload_n` | 加载int到栈 | `iload_1` |
| `lload_n` | 加载long到栈 | `lload_2` |
| `fload_n` | 加载float到栈 | `fload_3` |
| `dload_n` | 加载double到栈 | `dload_0` |
| `istore_n` | 存储int到局部变量 | `istore_1` |

#### 运算指令

| 指令 | 作用 | 示例 |
|-----|------|------|
| `iadd` | int加法 | `count + 1` |
| `isub` | int减法 | `count - 1` |
| `imul` | int乘法 | `count * 2` |
| `idiv` | int除法 | `count / 2` |
| `iinc` | int自增 | `count++` |

#### 类型转换指令

| 指令 | 作用 | 示例 |
|-----|------|------|
| `i2l` | int转long | `(long)count` |
| `i2f` | int转float | `(float)count` |
| `l2i` | long转int | `(int)longValue` |

#### 对象创建和访问指令

| 指令 | 作用 | 示例 |
|-----|------|------|
| `new` | 创建对象 | `new User()` |
| `getfield` | 获取实例字段 | `this.count` |
| `putfield` | 设置实例字段 | `this.count = 10` |
| `getstatic` | 获取静态字段 | `Math.PI` |
| `putstatic` | 设置静态字段 | `Count.total = 10` |

#### 方法调用指令

| 指令 | 作用 | 使用场景 |
|-----|------|---------|
| `invokevirtual` | 调用实例方法 | `user.getName()` |
| `invokespecial` | 调用构造器、私有方法、父类方法 | `super.method()` |
| `invokestatic` | 调用静态方法 | `Math.max()` |
| `invokeinterface` | 调用接口方法 | `list.add()` |
| `invokedynamic` | 调用动态方法 | Lambda表达式 |

---

## 五、字节码的实际应用

### 5.1 字节码增强（Bytecode Enhancement）

**应用场景**：
- AOP（面向切面编程）
- 性能监控（方法耗时统计）
- 动态代理
- ORM框架（Hibernate懒加载）

**常用工具**：
- ASM：直接操作字节码
- Javassist：高级API
- ByteBuddy：现代化字节码操作库

### 5.2 性能优化

**理解字节码有助于**：
- 避免不必要的装箱/拆箱
- 优化循环和条件判断
- 理解JIT编译的优化点

**示例**：
```java
// 方案1：自动装箱（慢）
Integer sum = 0;
for (int i = 0; i < 1000000; i++) {
    sum += i;  // 每次循环都装箱/拆箱
}

// 方案2：基本类型（快）
int sum = 0;
for (int i = 0; i < 1000000; i++) {
    sum += i;  // 直接int运算
}
```

**字节码对比**：
```
方案1：
    iload
    invokevirtual Integer.intValue()  ← 拆箱
    iadd
    invokestatic Integer.valueOf()     ← 装箱

方案2：
    iload
    iadd                                ← 直接运算
```

---

## 六、常见问题

### ❓ 问题1：为什么.class文件比.java大？

**原因**：
1. **常量池**：存储所有字符串、类名、方法名等
2. **元数据**：行号表、局部变量表、异常表
3. **完整类型信息**：泛型、注解等

**示例**：
```java
// HelloWorld.java (119字节)
public class HelloWorld {
    public static void main(String[] args) {
        System.out.println("Hello, World!");
    }
}

// HelloWorld.class (426字节)
// 包含：常量池、方法表、行号表、局部变量表等
```

### ❓ 问题2：字节码可以反编译成源代码吗？

**可以**，但不完美：
- 局部变量名丢失（除非保留调试信息）
- 注释全部丢失
- 代码结构可能不同

**工具**：
- JD-GUI：可视化反编译
- CFR：命令行反编译

### ❓ 问题3：字节码的安全性如何？

**JVM的字节码校验**：
- 类型安全检查
- 栈溢出检查
- 跳转指令检查
- 访问权限检查

**防止**：
- 恶意代码执行
- 类型混淆攻击
- 栈溢出攻击

---

## 总结

### 核心要点回顾

1. **字节码的本质**
   - 介于源代码和机器码之间
   - 平台无关、紧凑高效
   - JVM的执行单元

2. **javac编译过程**
   - 词法分析 → 语法分析 → 语义分析 → 字节码生成
   - 生成class文件

3. **class文件格式**
   - 魔数：0xCAFEBABE
   - 版本号、常量池、方法表等
   - 严格按照JVM规范

4. **字节码指令**
   - 加载存储、运算、方法调用等
   - 基于操作数栈的执行模型

### 思考题

1. 为什么Java需要编译成字节码，而不是直接解释执行源代码？
2. 字节码的"平台无关性"是如何实现的？
3. 了解字节码对日常开发有什么帮助？

### 下一篇预告

下一篇《JVM、JRE、JDK三者的关系与区别》，我们将探讨：
- JVM、JRE、JDK的定义
- 三者的包含关系
- 如何选择合适的版本
- 开发环境配置

---

## 参考资料

- [The Java Virtual Machine Specification - Chapter 4: The class File Format](https://docs.oracle.com/javase/specs/jvms/se17/html/jvms-4.html)
- [The Java Virtual Machine Specification - Chapter 6: The JVM Instruction Set](https://docs.oracle.com/javase/specs/jvms/se17/html/jvms-6.html)
- 《深入理解Java虚拟机（第3版）》- 周志明，第6章
- [ASM字节码操作框架](https://asm.ow2.io/)

---

**欢迎在评论区分享你对字节码的理解！**
