---
title: "程序计数器：最小的内存区域"
date: 2025-11-21T20:00:00+08:00
draft: false
tags: ["JVM", "内存管理", "程序计数器"]
categories: ["技术"]
description: "深入理解程序计数器（PC寄存器）的作用、工作原理，以及为什么它是JVM中唯一不会发生OutOfMemoryError的内存区域"
series: ["JVM从入门到精通"]
weight: 12
stage: 3
stageTitle: "内存结构篇"
---

## 引言：一个被忽视的关键角色

在JVM的5大内存区域中，**程序计数器（Program Counter Register）** 是最小、最简单的一个，但却承担着至关重要的使命：

- 它记录着当前线程正在执行的字节码指令地址
- 它保证了多线程环境下每个线程能够独立执行
- 它是JVM中 **唯一不会发生OutOfMemoryError** 的内存区域

如果没有程序计数器，多线程程序将无法正常运行。本文将深入理解这个小而美的内存区域。

---

## 什么是程序计数器？

### 核心定义

**程序计数器（PC Register）** 是一块较小的内存空间，可以看作是 **当前线程所执行字节码的行号指示器**。

在JVM的概念模型中，字节码解释器工作时就是通过改变这个计数器的值来选取下一条需要执行的字节码指令。

### 第一性原理：为什么需要程序计数器？

从计算机组成原理的角度看：
- CPU执行指令需要知道 **"下一条指令在哪里"**
- 传统CPU使用 **PC寄存器（Program Counter）** 存储下一条指令地址
- JVM作为虚拟机，也需要类似的机制来 **跟踪字节码执行位置**

**核心作用**：
1. **记录执行位置**：存储当前线程正在执行的字节码指令地址
2. **支持线程切换**：多线程环境下，每个线程有独立的程序计数器，保证线程切换后能恢复到正确位置
3. **支持分支跳转**：循环、异常处理、方法返回等都依赖程序计数器

---

## 程序计数器的工作原理

### 字节码执行示例

让我们通过一个简单的例子理解程序计数器的工作：

```java
public class PCDemo {
    public static void main(String[] args) {
        int a = 1;
        int b = 2;
        int c = a + b;
        System.out.println(c);
    }
}
```

**编译后的字节码**（使用 `javap -c PCDemo.class` 查看）：

```
public static void main(java.lang.String[]);
  Code:
     0: iconst_1          // 将整数1压入操作数栈
     1: istore_1          // 将栈顶值存储到局部变量表slot 1（变量a）
     2: iconst_2          // 将整数2压入操作数栈
     3: istore_2          // 将栈顶值存储到局部变量表slot 2（变量b）
     4: iload_1           // 从局部变量表slot 1加载变量a
     5: iload_2           // 从局部变量表slot 2加载变量b
     6: iadd              // 将栈顶两个int值相加
     7: istore_3          // 将结果存储到局部变量表slot 3（变量c）
     8: getstatic #2      // 获取静态字段 System.out
    11: iload_3           // 加载变量c
    12: invokevirtual #3 // 调用println方法
    15: return            // 方法返回
```

**程序计数器的变化过程**：

```
执行阶段     字节码指令      程序计数器值    说明
─────────────────────────────────────────────────
初始化       -              0              指向第一条指令
执行 int a=1  iconst_1      0 → 1          将1压栈，计数器+1
             istore_1      1 → 2          存储到变量a
执行 int b=2  iconst_2      2 → 3          将2压栈
             istore_2      3 → 4          存储到变量b
执行 c=a+b   iload_1       4 → 5          加载变量a
             iload_2       5 → 6          加载变量b
             iadd          6 → 7          执行加法
             istore_3      7 → 8          存储到变量c
打印输出     getstatic     8 → 11         获取System.out
             iload_3       11 → 12        加载变量c
             invokevirtual 12 → 15        调用println
方法结束     return        15 → -         方法返回
```

**关键理解**：
- 程序计数器始终指向 **下一条要执行的字节码指令地址**
- 指令执行后，计数器自动更新（通常+1，跳转指令除外）
- 分支、循环、异常等会改变计数器的跳转方向

---

### 多线程环境下的程序计数器

**为什么每个线程需要独立的程序计数器？**

因为 **JVM的多线程是通过线程轮流切换、分配处理器执行时间的方式实现的**。在任何确定时刻，一个处理器核心只会执行一条线程中的指令。

**示例：两个线程并发执行**

```java
public class MultiThreadDemo {
    public static void main(String[] args) {
        new Thread(() -> {
            int x = 1;
            int y = 2;
            int z = x + y;
        }, "Thread-1").start();

        new Thread(() -> {
            int a = 10;
            int b = 20;
            int c = a + b;
        }, "Thread-2").start();
    }
}
```

**内存布局**：

```
┌─────────────────────────────────────────────┐
│              Thread-1                       │
│  ┌────────────────────┐                     │
│  │   程序计数器        │  值: 6 (指向iadd)   │
│  └────────────────────┘                     │
│  ┌────────────────────┐                     │
│  │   虚拟机栈          │                     │
│  │  · x = 1           │                     │
│  │  · y = 2           │                     │
│  └────────────────────┘                     │
└─────────────────────────────────────────────┘

┌─────────────────────────────────────────────┐
│              Thread-2                       │
│  ┌────────────────────┐                     │
│  │   程序计数器        │  值: 4 (指向iload_1)│
│  └────────────────────┘                     │
│  ┌────────────────────┐                     │
│  │   虚拟机栈          │                     │
│  │  · a = 10          │                     │
│  │  · b = 20          │                     │
│  └────────────────────┘                     │
└─────────────────────────────────────────────┘
```

**线程切换过程**：

1. **Thread-1执行中**（PC=6，准备执行iadd指令）
2. **CPU时间片到期，切换到Thread-2**
3. **Thread-2从PC=4处继续执行**（加载变量a）
4. **Thread-2时间片到期，切换回Thread-1**
5. **Thread-1从PC=6处继续执行**（执行iadd，因为PC值已保存）

**关键理解**：
- 每个线程都有独立的程序计数器（**线程私有**）
- 线程切换时，程序计数器保存了当前执行位置
- 恢复线程时，从程序计数器存储的位置继续执行

---

## 程序计数器的核心特点

### 1️⃣ 线程私有

**每个线程都有独立的程序计数器**，互不影响。

**验证代码**：

```java
public class PCThreadPrivate {
    public static void main(String[] args) {
        for (int i = 0; i < 3; i++) {
            new Thread(() -> {
                for (int j = 0; j < 1000; j++) {
                    // 每个线程独立执行，不会互相干扰
                    int result = j * 2;
                }
            }).start();
        }
    }
}
```

每个线程执行循环时，程序计数器独立记录执行位置，不会混乱。

---

### 2️⃣ 占用内存极小

程序计数器占用的内存空间非常小，通常只有 **几十字节**。

**为什么这么小？**
- 只存储一个整数（字节码指令地址）
- 不存储对象引用或复杂数据结构
- 不需要GC管理

---

### 3️⃣ 唯一不会OOM的区域

**为什么程序计数器不会发生OutOfMemoryError？**

因为程序计数器的大小是 **固定的**，且非常小：
- 不管程序多复杂，程序计数器只存储一个指令地址
- 不会随着程序运行而增长
- 没有内存分配和回收的过程

**对比其他内存区域**：
| 内存区域 | 是否会OOM | 原因 |
|---------|----------|------|
| 程序计数器 | ❌ 不会 | 大小固定，不随程序运行增长 |
| 虚拟机栈 | ✅ 会 | 栈深度超限（如递归太深） |
| 堆 | ✅ 会 | 对象实例过多，内存耗尽 |
| 方法区 | ✅ 会 | 类加载过多，元空间溢出 |
| 直接内存 | ✅ 会 | NIO操作过度，堆外内存耗尽 |

---

### 4️⃣ Native方法执行时的特殊行为

**当线程执行Native方法时，程序计数器的值为空（Undefined）。**

**为什么？**
- Native方法是用C/C++编写的，不是Java字节码
- JVM无法追踪Native方法的执行位置
- Native方法由本地方法栈管理，不需要程序计数器

**示例**：

```java
public class NativeMethodDemo {
    public static void main(String[] args) {
        // System.currentTimeMillis()是Native方法
        long time = System.currentTimeMillis();

        // 执行Native方法时，程序计数器值为Undefined
        // 执行完毕返回后，程序计数器恢复正常值
    }
}
```

**执行流程**：

```
Java方法执行       →  程序计数器 = 8 (invokestatic指令地址)
调用Native方法     →  程序计数器 = Undefined
Native方法执行中   →  程序计数器 = Undefined
Native方法返回     →  程序计数器 = 11 (下一条指令地址)
继续Java方法执行   →  程序计数器 = 11, 12, ...
```

---

## 实战场景：程序计数器的应用

### 场景1：异常处理

异常发生时，程序计数器会跳转到异常处理代码：

```java
public void exceptionDemo() {
    try {
        int result = 10 / 0;  // PC = 5, 发生ArithmeticException
    } catch (ArithmeticException e) {
        // PC跳转到catch块的第一条指令
        System.out.println("除零错误");
    }
}
```

**程序计数器跳转**：
- 正常执行：PC = 0 → 1 → 2 → 3 → 4 → 5
- 异常发生：PC = 5 → 跳转到catch块 → 10 → 11 → ...

---

### 场景2：循环控制

循环依赖程序计数器的跳转机制：

```java
public void loopDemo() {
    for (int i = 0; i < 3; i++) {
        System.out.println(i);
    }
}
```

**字节码示例**：

```
0: iconst_0         // i = 0
1: istore_1         // 存储i
2: iload_1          // 加载i
3: iconst_3         // 加载3
4: if_icmpge 15     // 如果 i >= 3, 跳转到15（循环结束）
7: getstatic #2     // 获取System.out
10: iload_1         // 加载i
11: invokevirtual #3 // 调用println
14: goto 2          // 跳转回2（继续循环）
15: return          // 循环结束
```

**程序计数器变化**：
- 第一次循环：0 → 1 → 2 → 3 → 4 → 7 → 10 → 11 → 14 → **跳回2**
- 第二次循环：2 → 3 → 4 → 7 → 10 → 11 → 14 → **跳回2**
- 第三次循环：2 → 3 → 4 → 7 → 10 → 11 → 14 → **跳回2**
- 循环结束：2 → 3 → 4 → **跳到15** → return

---

## 常见问题与误区

### ❌ 误区1：程序计数器存储的是源代码行号

**真相**：程序计数器存储的是 **字节码指令地址**，不是源代码行号。

**源代码行号**通过LineNumberTable存储在字节码文件中，用于调试和异常堆栈。

---

### ❌ 误区2：程序计数器占用很大内存

**真相**：程序计数器占用内存极小（几十字节），可以忽略不计。

---

### ❌ 误区3：所有内存区域都可能发生OOM

**真相**：程序计数器是 **唯一不会发生OutOfMemoryError** 的内存区域。

---

## 总结

### 核心要点

1. **程序计数器是JVM中最小的内存区域**，存储当前线程正在执行的字节码指令地址

2. **线程私有**：每个线程有独立的程序计数器，保证多线程环境下线程切换的正确性

3. **唯一不会OOM**：程序计数器大小固定，不会随程序运行而增长

4. **Native方法执行时为空**：JVM无法追踪Native方法的执行位置

5. **支持分支跳转**：循环、异常处理、方法调用等都依赖程序计数器

### 与下篇文章的衔接

下一篇文章，我们将深入学习 **虚拟机栈（Java Virtual Machine Stack）**，理解方法调用时栈帧的创建与销毁，以及局部变量表、操作数栈的工作原理。

---

## 参考资料

- 《深入理解Java虚拟机（第3版）》- 周志明
- [Java虚拟机规范（Java SE 8版）](https://docs.oracle.com/javase/specs/jvms/se8/html/)
- [程序计数器 - Wikipedia](https://en.wikipedia.org/wiki/Program_counter)

---

> **下一篇预告**：《虚拟机栈：方法执行的内存模型》
> 深入理解栈帧结构、局部变量表、操作数栈，以及StackOverflowError的根源。
